quality_checks/__init__.py
quality_checks/data_types.py
quality_checks/duplicates.py
quality_checks/missing_values.py
quality_checks/outliers.py
utils/__init__.py
utils/data_loader.py
utils/numpy_utils.py
utils/report_generator.py
data_quality_assessment-0.1.0.dist-info/METADATA
data_quality_assessment-0.1.0.dist-info/WHEEL
data_quality_assessment-0.1.0.dist-info/entry_points.txt
data_quality_assessment-0.1.0.dist-info/top_level.txt
data_quality_assessment-0.1.0.dist-info/RECORD
