Metadata-Version: 2.4
Name: data-quality-assessment
Version: 0.1.0
Summary: A powerful web application for assessing data quality issues
Home-page: https://github.com/godwinwa/data-quality-app
Author: Godwin Wa
Author-email: godwinacheampong89@gmail.com
Project-URL: Bug Reports, https://github.com/godwinwa/data-quality-app/issues
Project-URL: Source, https://github.com/godwinwa/data-quality-app
Classifier: Programming Language :: Python :: 3
Classifier: License :: OSI Approved :: MIT License
Classifier: Operating System :: OS Independent
Classifier: Framework :: Flask
Classifier: Topic :: Scientific/Engineering :: Information Analysis
Classifier: Development Status :: 4 - Beta
Classifier: Intended Audience :: Developers
Classifier: Intended Audience :: Science/Research
Requires-Python: >=3.8
Requires-Dist: blinker==1.9.0
Requires-Dist: cachelib==0.13.0
Requires-Dist: click==8.1.8
Requires-Dist: Flask==3.1.0
Requires-Dist: Flask-Session==0.8.0
Requires-Dist: gunicorn==23.0.0
Requires-Dist: itsdangerous==2.2.0
Requires-Dist: Jinja2==3.1.6
Requires-Dist: MarkupSafe==3.0.2
Requires-Dist: msgspec==0.19.0
Requires-Dist: narwhals==1.34.1
Requires-Dist: numpy==2.2.4
Requires-Dist: packaging==24.2
Requires-Dist: pandas==2.2.3
Requires-Dist: plotly==6.0.1
Requires-Dist: python-dateutil==2.9.0.post0
Requires-Dist: pytz==2025.2
Requires-Dist: setuptools==78.1.0
Requires-Dist: six==1.17.0
Requires-Dist: tzdata==2025.2
Requires-Dist: Werkzeug==3.1.3
Dynamic: author
Dynamic: author-email
Dynamic: classifier
Dynamic: description
Dynamic: description-content-type
Dynamic: home-page
Dynamic: project-url
Dynamic: requires-dist
Dynamic: requires-python
Dynamic: summary
